Metadata-Version: 2.1
Name: geophotos
Version: 0.50
Summary: A package to pull, plot, and analyze coordinates from photos.
Home-page: https://github.com/jakebrehm/geophotos
Author: Jake Brehm
Author-email: code@jakebrehm.com
License: MIT
Platform: UNKNOWN
Classifier: Programming Language :: Python :: 3.7
Classifier: Operating System :: OS Independent
Provides-Extra: geopandas
